hg_oap/__init__.py
hg_oap/assets/__init__.py
hg_oap/assets/asset.py
hg_oap/assets/currency.py
hg_oap/dates/__init__.py
hg_oap/dates/calendar.py
hg_oap/dates/date_services.py
hg_oap/dates/dgen.py
hg_oap/dates/dt_utils.py
hg_oap/dates/tenor.py
hg_oap/impl/__init__.py
hg_oap/impl/assets/__init__.py
hg_oap/impl/assets/commodities.py
hg_oap/impl/assets/currency.py
hg_oap/impl/dates/__init__.py
hg_oap/impl/dates/lme_calendar.py
hg_oap/impl/instruments/__init__.py
hg_oap/impl/instruments/cash.py
hg_oap/impl/instruments/commodity.py
hg_oap/impl/instruments/futures/__init__.py
hg_oap/impl/instruments/futures/commodity_futures.py
hg_oap/impl/instruments/futures/lme.py
hg_oap/instrument_data_service/__init__.py
hg_oap/instrument_data_service/instrument_data_service.py
hg_oap/instruments/__init__.py
hg_oap/instruments/calendar_spread.py
hg_oap/instruments/cash.py
hg_oap/instruments/forward.py
hg_oap/instruments/future.py
hg_oap/instruments/future_spread.py
hg_oap/instruments/fx.py
hg_oap/instruments/index.py
hg_oap/instruments/instrument.py
hg_oap/instruments/physical.py
hg_oap/orders/__init__.py
hg_oap/orders/order.py
hg_oap/orders/order_request_response_events.py
hg_oap/orders/order_service.py
hg_oap/orders/order_type.py
hg_oap/portfolio/__init__.py
hg_oap/portfolio/portfolio.py
hg_oap/position/__init__.py
hg_oap/position/position.py
hg_oap/pricing/__init__.py
hg_oap/pricing/price.py
hg_oap/pricing/pricing_services.py
hg_oap/pricing_service/__init__.py
hg_oap/pricing_service/data_types.py
hg_oap/pricing_service/error_pricing_model.py
hg_oap/pricing_service/price.py
hg_oap/pricing_service/price_mesh_ui.py
hg_oap/pricing_service/price_service.py
hg_oap/pricing_service/price_stream_operators.py
hg_oap/pricing_service/pricing_model_choice.py
hg_oap/pricing_service/pricing_regime_context.py
hg_oap/pricing_service/timed_value.py
hg_oap/pricing_service/timed_value_operators.py
hg_oap/pricing_service/utils.py
hg_oap/quanity/__init__.py
hg_oap/quanity/conversion.py
hg_oap-0.1.13.dist-info/LICENSE
hg_oap-0.1.13.dist-info/METADATA
hg_oap-0.1.13.dist-info/WHEEL
hg_oap-0.1.13.dist-info/RECORD
