Metadata-Version: 2.3
Name: hg_oap
Version: 0.1.13
Summary: A library to faciliate building order and pricing strategies
License: MIT
Keywords: reactive,graph,fpg,forward propogating graph,time series,functional reactive programming,order,pricing,oms
Author: Howard Henson
Author-email: howard@henson.me.uk
Requires-Python: >=3.11
Classifier: Development Status :: 3 - Alpha
Classifier: License :: OSI Approved :: MIT License
Classifier: Programming Language :: Python
Classifier: Programming Language :: Python :: 3
Classifier: Programming Language :: Python :: 3.11
Classifier: Programming Language :: Python :: 3.12
Classifier: Programming Language :: Python :: 3.13
Classifier: Programming Language :: Python :: Implementation :: CPython
Requires-Dist: hgraph[web] (>=0.4.0)
Requires-Dist: holidays (>=0.56)
Project-URL: Changelog, https://github.com/hhenson/hg_oap/blob/main/CHANGELOG.md
Project-URL: Documentation, https://hhenson.readthedocs.io
Project-URL: Homepage, https://github.com/hhenson/hg_oap
Project-URL: Issues, https://github.com/hhenson/hg_oap/blob/main/ISSUES.md
Project-URL: Repository, https://github.com/hhenson/hg_oap.git
